jupyterlab_media_capture/__init__.py
jupyterlab_media_capture/_version.py
jupyterlab_media_capture/handlers.py
jupyterlab_media_capture/labextension/package.json
jupyterlab_media_capture/labextension/static/212.c1ae61bf91ab86b8abab.js
jupyterlab_media_capture/labextension/static/212.c1ae61bf91ab86b8abab.js.LICENSE.txt
jupyterlab_media_capture/labextension/static/534.58ab1b7e0c4970916ab7.js
jupyterlab_media_capture/labextension/static/743.ff2f34a2e8fdb39fde4d.js
jupyterlab_media_capture/labextension/static/remoteEntry.7ed0ee0b90d49613e73a.js
jupyterlab_media_capture/labextension/static/style.js
jupyterlab_media_capture-0.4.0.data/data/etc/jupyter/jupyter_server_config.d/jupyterlab_media_capture.json
jupyterlab_media_capture-0.4.0.data/data/share/jupyter/labextensions/jupyterlab-media-capture/install.json
jupyterlab_media_capture-0.4.0.data/data/share/jupyter/labextensions/jupyterlab-media-capture/package.json
jupyterlab_media_capture-0.4.0.data/data/share/jupyter/labextensions/jupyterlab-media-capture/static/212.c1ae61bf91ab86b8abab.js
jupyterlab_media_capture-0.4.0.data/data/share/jupyter/labextensions/jupyterlab-media-capture/static/212.c1ae61bf91ab86b8abab.js.LICENSE.txt
jupyterlab_media_capture-0.4.0.data/data/share/jupyter/labextensions/jupyterlab-media-capture/static/534.58ab1b7e0c4970916ab7.js
jupyterlab_media_capture-0.4.0.data/data/share/jupyter/labextensions/jupyterlab-media-capture/static/743.ff2f34a2e8fdb39fde4d.js
jupyterlab_media_capture-0.4.0.data/data/share/jupyter/labextensions/jupyterlab-media-capture/static/remoteEntry.7ed0ee0b90d49613e73a.js
jupyterlab_media_capture-0.4.0.data/data/share/jupyter/labextensions/jupyterlab-media-capture/static/style.js
jupyterlab_media_capture-0.4.0.dist-info/LICENSE
jupyterlab_media_capture-0.4.0.dist-info/METADATA
jupyterlab_media_capture-0.4.0.dist-info/WHEEL
jupyterlab_media_capture-0.4.0.dist-info/top_level.txt
jupyterlab_media_capture-0.4.0.dist-info/RECORD
