Metadata-Version: 2.1
Name: jupyterlab-media-capture
Version: 0.4.0
Summary: Capture media using browser APIs within JupyterLab
Home-page: https://github.com/IBM/jupyterlab-media-capture
Author: James Reeve
Author-email: james.reeve@ibm.com
License: Apache-2.0
Keywords: Jupyter,JupyterLab,JupyterLab3
Platform: Linux
Platform: Mac OS X
Platform: Windows
Classifier: License :: OSI Approved :: BSD License
Classifier: Programming Language :: Python
Classifier: Programming Language :: Python :: 3
Classifier: Programming Language :: Python :: 3.6
Classifier: Programming Language :: Python :: 3.7
Classifier: Programming Language :: Python :: 3.8
Classifier: Programming Language :: Python :: 3.9
Classifier: Framework :: Jupyter
Requires-Python: >=3.6
Requires-Dist: jupyterlab (~=3.0)
